{"Bestelldatum und Uhrzeit": "2023-12-03 17:49:21", "Kunde": "ZRM", "Auftragsnummer": "ZRM20231203174921", "Sonderwunsch": "f\u00fcr mich selbst", "Variante nach Bestellung": {"F\u00fchrerhaus": "Blau", "Sidepipes": "Blau", "Container 1": "Blau", "Container 2": "Blau", "Container 3": "Blau", "Container 4": "Blau"}, "Kundentakt": "45"}
{"Bestelldatum und Uhrzeit": "2023-12-03 17:49:44", "Kunde": "Rj", "Auftragsnummer": "RJ20231203174944", "Sonderwunsch": "f\u00fcr seine Mutter", "Variante nach Bestellung": {"F\u00fchrerhaus": "Blau", "Sidepipes": "Blau", "Container 1": "Blau", "Container 2": "Blau", "Container 3": "Blau", "Container 4": "Blau"}, "Kundentakt": "65"}
{"Bestelldatum und Uhrzeit": "2023-12-03 17:50:16", "Kunde": "Dan", "Auftragsnummer": "DAN20231203175016", "Sonderwunsch": "f\u00fcr seinen Bruder", "Variante nach Bestellung": {"F\u00fchrerhaus": "Blau", "Sidepipes": "Blau", "Container 1": "Gelb", "Container 2": "Blau", "Container 3": "Blau", "Container 4": "Blau"}, "Kundentakt": "50"}
